{"Aziraphale4201": "__label__0", "Crowley1678": "__label__1", "Crowley4680": "__label__2", "一维": "__label__3", "T·S·艾略特": "__label__4", "三岛由纪夫": "__label__5", "上野千鹤子": "__label__6", "东野圭吾": "__label__7", "丹尼尔·凯斯": "__label__8", "丹尼尔·笛福": "__label__9", "乔伊斯": "__label__10", "乔叟": "__label__11", "乔治·奥威尔": "__label__12", "乔纳森·斯威夫特": "__label__13", "亨利·大卫·梭罗": "__label__14", "伍迪·艾伦": "__label__15", "伏尼契": "__label__16", "但丁": "__label__17", "儒勒·凡尔纳": "__label__18", "列夫托尔斯泰": "__label__19", "刘易斯·卡罗尔": "__label__20", "加缪": "__label__21", "加西亚·马尔克斯": "__label__22", "博尔赫斯": "__label__23", "卡勒德·胡赛尼": "__label__24", "卡夫卡": "__label__25", "史蒂芬·金": "__label__26", "司汤达": "__label__27", "埃克多·马洛": "__label__28", "埃莱娜·费兰特": "__label__29", "塞万提斯": "__label__30", "塞林格": "__label__31", "夏多布里昂": "__label__32", "夏洛蒂·勃朗特": "__label__33", "大仲马": "__label__34", "大卫·林奇": "__label__35", "大卫·米切尔": "__label__36", "大卫·赫伯特·劳伦斯": "__label__37", "太宰治": "__label__38", "契诃夫": "__label__39", "奥尔德斯·赫胥黎": "__label__40", "奥斯特洛夫斯基": "__label__41", "安东尼·伯吉斯": "__label__42", "小仲马": "__label__43", "尼尔·盖曼": "__label__44", "屠格涅夫": "__label__45", "岩井俊二": "__label__46", "川端康成": "__label__47", "巴尔扎克": "__label__48", "席勒": "__label__49", "弗兰克·赫伯特": "__label__50", "弗兰克·鲍姆": "__label__51", "弗兰纳里·奥康纳": "__label__52", "弗拉基米尔·纳博科夫": "__label__53", "托尔金": "__label__54", "托马斯·哈代": "__label__55", "托马斯·哈里斯": "__label__56", "扬·马特尔": "__label__57", "拜伦": "__label__58", "斯蒂芬·茨威格": "__label__59", "普希金": "__label__60", "本尼迪克特": "__label__61", "村上春树": "__label__62", "杰克·伦敦": "__label__63", "杰克·凯鲁亚克": "__label__64", "柏拉图": "__label__65", "查克·帕拉纽克": "__label__66", "柯南道尔": "__label__67", "欧·亨利": "__label__68", "歌德": "__label__69", "毛姆": "__label__70", "沃尔特•司各特": "__label__71", "法布尔": "__label__72", "泰戈尔": "__label__73", "海伦·凯勒": "__label__74", "海明威": "__label__75", "海莲·汉芙": "__label__76", "渡边淳一": "__label__77", "温斯顿·格鲁姆": "__label__78", "爱伦·坡": "__label__79", "爱德华·摩根·福斯特": "__label__80", "狄更斯": "__label__81", "玛格丽特·杜拉斯": "__label__82", "玛格丽特·米切尔": "__label__83", "瓦尔特·惠特曼": "__label__84", "福楼拜": "__label__85", "穆罕默德": "__label__86", "简·奥斯汀": "__label__87", "米兰·昆德拉": "__label__88", "米哈依尔·肖洛霍夫": "__label__89", "米歇尔·德·蒙田": "__label__90", "紫式部": "__label__91", "约翰·伯恩": "__label__92", "纪德": "__label__93", "维克多·雨果": "__label__94", "罗曼·罗兰": "__label__95", "聂鲁达": "__label__96", "艾米莉·勃朗特": "__label__97", "艾萨克•阿西莫夫": "__label__98", "芥川龙之介": "__label__99", "荷马": "__label__100", "莎士比亚": "__label__101", "莫泊桑": "__label__102", "菲兹杰拉德": "__label__103", "菲茨杰拉德": "__label__104", "萨克雷": "__label__105", "萨德": "__label__106", "蒲宁": "__label__107", "薄伽丘": "__label__108", "西奥多·德莱塞": "__label__109", "西德尼·谢尔顿": "__label__110", "谷崎润一郎": "__label__111", "费尔南多·佩索阿": "__label__112", "赫尔曼·黑塞": "__label__113", "路易莎·梅·奥尔科特": "__label__114", "达夫妮·杜穆里埃": "__label__115", "道格拉斯·亚当斯": "__label__116", "阿加莎·克里斯蒂": "__label__117", "阿瑟·克拉克": "__label__118", "阿瑟·高顿": "__label__119", "陀思妥耶夫斯基": "__label__120", "雅洛斯拉夫·哈谢克": "__label__121", "雷蒙德·卡佛": "__label__122", "霍桑": "__label__123", "霍达": "__label__124", "马克·吐温": "__label__125", "马赛尔·普鲁斯特": "__label__126", "马里奥·普佐": "__label__127", "高尔基": "__label__128"}